uservice_utils/logging.py
uservice_utils/__init__.py
uservice_utils/queue.py
uservice_utils/tests/__init__.py
uservice_utils/tests/test_queue.py
uservice_utils/tests/test_logging.py
uservice_utils-1.0.3.dist-info/DESCRIPTION.rst
uservice_utils-1.0.3.dist-info/RECORD
uservice_utils-1.0.3.dist-info/metadata.json
uservice_utils-1.0.3.dist-info/METADATA
uservice_utils-1.0.3.dist-info/top_level.txt
uservice_utils-1.0.3.dist-info/WHEEL
