Metadata-Version: 2.0
Name: uservice-utils
Version: 1.0.3
Summary: Utilities for building micro-services.
Home-page: https://launchpad.net/uservice-utils
Author: Canonical CI Engineering Team
Author-email: canonical-ci-engineering@lists.launchpad.net
License: GPLv3
Platform: UNKNOWN
Classifier: Development Status :: 5 - Production/Stable
Classifier: Environment :: Console
Classifier: Intended Audience :: Developers
Classifier: License :: OSI Approved :: GNU General Public License v3 (GPLv3)
Classifier: Programming Language :: Python :: 3 :: Only
Classifier: Topic :: Software Development
